pybuildingcluster/__init__.py
pybuildingcluster/cli.py
pybuildingcluster/exceptions.py
pybuildingcluster/types.py
pybuildingcluster/core/__init__.py
pybuildingcluster/core/clustering.py
pybuildingcluster/core/models.py
pybuildingcluster/core/optimization.py
pybuildingcluster/core/regression.py
pybuildingcluster/core/sensitivity.py
pybuildingcluster/data/__init__.py
pybuildingcluster/data/loader.py
pybuildingcluster/utils/__init__.py
pybuildingcluster/utils/config.py
pybuildingcluster-1.7.dist-info/licenses/AUTHORS.rst
pybuildingcluster-1.7.dist-info/licenses/LICENSE
pybuildingcluster-1.7.dist-info/METADATA
pybuildingcluster-1.7.dist-info/WHEEL
pybuildingcluster-1.7.dist-info/entry_points.txt
pybuildingcluster-1.7.dist-info/top_level.txt
pybuildingcluster-1.7.dist-info/RECORD
