Metadata-Version: 2.4
Name: pybuildingcluster
Version: 1.7
Summary: A Python library for clustering energy performance data and conducting sensitivity analysis on building clusters
Home-page: https://github.com/EURAC-EEBgroup/pybuildingcluster
Author: Daniele Antonucci
Author-email: daniele.antonucci@eurac.edu
Project-URL: Bug Reports, https://github.com/EURAC-EEBgroup/pybuildingcluster/issues
Project-URL: Source, https://github.com/EURAC-EEBgroup/pybuildingcluster
Project-URL: Documentation, https://github.com/EURAC-EEBgroup/pybuildingcluster
Keywords: clustering sensitivity analysis energy efficiency buildings machine learning
Classifier: Development Status :: 4 - Beta
Classifier: Intended Audience :: Science/Research
Classifier: Intended Audience :: Developers
Classifier: License :: OSI Approved :: MIT License
Classifier: Operating System :: OS Independent
Classifier: Programming Language :: Python :: 3
Classifier: Programming Language :: Python :: 3.8
Classifier: Programming Language :: Python :: 3.9
Classifier: Programming Language :: Python :: 3.10
Classifier: Programming Language :: Python :: 3.11
Classifier: Programming Language :: Python :: 3.12
Classifier: Topic :: Scientific/Engineering
Classifier: Topic :: Scientific/Engineering :: Artificial Intelligence
Requires-Python: >=3.8
License-File: LICENSE
License-File: AUTHORS.rst
Requires-Dist: numpy>=2.1.3
Requires-Dist: pandas>=2.2.3
Requires-Dist: scipy>=1.15.1
Requires-Dist: scikit-learn>=1.5.2
Requires-Dist: matplotlib>=3.10.3
Requires-Dist: seaborn>=0.13.2
Requires-Dist: plotly>=5.24.1
Requires-Dist: joblib>=1.4.2
Requires-Dist: tqdm>=4.60.0
Requires-Dist: xgboost>=2.1.4
Requires-Dist: lightgbm>=4.6.0
Requires-Dist: optuna>=4.3.0
Requires-Dist: pydantic>=2.7.2
Requires-Dist: python-dotenv>=1.0.0
Provides-Extra: dev
Requires-Dist: pytest>=6.0; extra == "dev"
Requires-Dist: pytest-cov>=2.10; extra == "dev"
Requires-Dist: black>=21.0; extra == "dev"
Requires-Dist: flake8>=3.8; extra == "dev"
Requires-Dist: mypy>=0.800; extra == "dev"
Requires-Dist: isort>=5.0; extra == "dev"
Provides-Extra: docs
Requires-Dist: sphinx>=4.0; extra == "docs"
Requires-Dist: sphinx-rtd-theme>=1.0; extra == "docs"
Provides-Extra: interactive
Requires-Dist: jupyter>=1.0.0; extra == "interactive"
Requires-Dist: ipywidgets>=7.6.0; extra == "interactive"
Dynamic: author
Dynamic: author-email
Dynamic: classifier
Dynamic: description
Dynamic: description-content-type
Dynamic: home-page
Dynamic: keywords
Dynamic: license-file
Dynamic: project-url
Dynamic: provides-extra
Dynamic: requires-dist
Dynamic: requires-python
Dynamic: summary
